math_stats_ml/autograders/assignment_12/__init__.py
math_stats_ml/autograders/assignment_12/prob_checks.py
math_stats_ml/autograders/assignment_12/sol.py
math_stats_ml/autograders/assignment_13/__init__.py
math_stats_ml/autograders/assignment_13/prob_checks.py
math_stats_ml/autograders/assignment_13/sol.py
math_stats_ml/gd/__init__.py
math_stats_ml/gd/gd_functions.py
math_stats_ml/gd/gd_utils.py
math_stats_ml-0.0.18.dist-info/LICENSE
math_stats_ml-0.0.18.dist-info/METADATA
math_stats_ml-0.0.18.dist-info/WHEEL
math_stats_ml-0.0.18.dist-info/top_level.txt
math_stats_ml-0.0.18.dist-info/RECORD
